django_dynamic_path/__init__.py
django_dynamic_path/tests/__init__.py
django_dynamic_path/tests/tests.py
django_dynamic_path/tests/urls.py
dummy_project/__init__.py
dummy_project/settings.py
dummy_project/urls.py
dummy_project/wsgi.py
django_dynamic_path-0.2.0.dist-info/LICENSE
django_dynamic_path-0.2.0.dist-info/METADATA
django_dynamic_path-0.2.0.dist-info/WHEEL
django_dynamic_path-0.2.0.dist-info/top_level.txt
django_dynamic_path-0.2.0.dist-info/RECORD
