Metadata-Version: 2.1
Name: django-dynamic-path
Version: 0.2.0
Summary: A django path() replacement enabling truly dynamic urls
Home-page: https://github.com/quadrant-newmedia/django_dynamic_path
Author: Alex Fischer
Author-email: alex@quadrant.net
License: UNKNOWN
Platform: UNKNOWN
Classifier: Programming Language :: Python :: 3
Classifier: License :: OSI Approved :: MIT License
Classifier: Operating System :: OS Independent
Requires-Python: >=3.7
Requires-Dist: Django (<6,>=3)
